[
  {
    "league": "ยูฟ่า แชมเปี้ยนส์ ลีก",
    "time": "00:45",
    "home": "สปอร์ติ้ง ลิสบอน",
    "hLogo": "https://www.siamsport.co.th/static/team-logo/14448.png",
    "away": "โบโด กลิมท์",
    "aLogo": "https://www.siamsport.co.th/static/team-logo/13694.png",
    "status": "upcoming",
    "link": "https://www.siamsport.co.th/matches/3838831"
  },
  {
    "league": "ยูฟ่า แชมเปี้ยนส์ ลีก",
    "time": "03:00",
    "home": "เชลซี",
    "hLogo": "https://www.siamsport.co.th/static/team-logo/9092.png",
    "away": "เปแอสเช",
    "aLogo": "https://www.siamsport.co.th/static/team-logo/10061.png",
    "status": "upcoming",
    "link": "https://www.siamsport.co.th/matches/3838828"
  },
  {
    "league": "ยูฟ่า แชมเปี้ยนส์ ลีก",
    "time": "03:00",
    "home": "แมนซิตี้",
    "hLogo": "https://www.siamsport.co.th/static/team-logo/9259.png",
    "away": "เรอัล มาดริด",
    "aLogo": "https://www.siamsport.co.th/static/team-logo/16110.png",
    "status": "upcoming",
    "link": "https://www.siamsport.co.th/matches/3838830"
  },
  {
    "league": "ยูฟ่า แชมเปี้ยนส์ ลีก",
    "time": "03:00",
    "home": "อาร์เซน่อล",
    "hLogo": "https://www.siamsport.co.th/static/team-logo/9002.png",
    "away": "ไบเออร์ เลเวอร์คูเซ่น",
    "aLogo": "https://www.siamsport.co.th/static/team-logo/10281.png",
    "status": "upcoming",
    "link": "https://www.siamsport.co.th/matches/3838825"
  },
  {
    "league": "แชมเปี้ยนชิพ อังกฤษ",
    "time": "02:45",
    "home": "วัตฟอร์ด",
    "hLogo": "https://www.siamsport.co.th/static/team-logo/9423.png",
    "away": "เร็กซ์แฮม",
    "aLogo": "https://www.siamsport.co.th/static/team-logo/9453.png",
    "status": "upcoming",
    "link": "https://www.siamsport.co.th/matches/3691582"
  }
]